py_cartes_io/__init__.py
py_cartes_io/maps.py
py_cartes_io-0.0.6.dist-info/METADATA
py_cartes_io-0.0.6.dist-info/WHEEL
py_cartes_io-0.0.6.dist-info/top_level.txt
py_cartes_io-0.0.6.dist-info/RECORD
