Metadata-Version: 2.1
Name: py-cartes-io
Version: 0.0.6
Summary: Cartes.io official Python API wrapper
Author: M Media
Author-email: <contact@mmediagroup.fr>
Keywords: python,cartes,cartes.io,api
Classifier: Development Status :: 3 - Alpha
Classifier: Intended Audience :: Education
Classifier: Programming Language :: Python :: 2
Classifier: Programming Language :: Python :: 3
Classifier: Operating System :: MacOS :: MacOS X
Classifier: Operating System :: Microsoft :: Windows
Requires-Dist: requests
Requires-Dist: time
